README.txt
setup.py
weechat_notifier/__init__.py
weechat_notifier/irc_message_processor.py
weechat_notifier/weechat_plugin.py
weechat_notifier.egg-info/PKG-INFO
weechat_notifier.egg-info/SOURCES.txt
weechat_notifier.egg-info/dependency_links.txt
weechat_notifier.egg-info/top_level.txt