Metadata-Version: 1.1
Name: weechat-notifier
Version: 0.1.46
Summary: Weechat Notification Plugin
Home-page: https://pypi.python.org/packages/source/w/weechat_notifier/weechat_notifier-0.1.46.tar.gz
Author: Fenton Travers
Author-email: fenton.travers@gmail.com
License: Creative Commons Attribution-Noncommercial-Share Alike license
Platform: UNKNOWN
Classifier: Programming Language :: Python :: 3.3
